silverpeak_exporter/__init__.py
silverpeak_exporter/args.py
silverpeak_exporter/collectors.py
silverpeak_exporter/file.py
silverpeak_exporter/logger.py
silverpeak_exporter/main.py
silverpeak_exporter/metrics.py
silverpeak_exporter/utls.py
silverpeak_exporter-0.1.8.dist-info/LICENSE
silverpeak_exporter-0.1.8.dist-info/METADATA
silverpeak_exporter-0.1.8.dist-info/WHEEL
silverpeak_exporter-0.1.8.dist-info/entry_points.txt
silverpeak_exporter-0.1.8.dist-info/RECORD
