Metadata-Version: 2.1
Name: silverpeak-exporter
Version: 0.1.8
Summary: Prometheus exporter for Silverpeak SD-WAN Appliances.
License: MIT
Author: IP Headers
Author-email: ipHeaders@users.noreply.github.com
Requires-Python: >=3.9,<4.0
Classifier: License :: OSI Approved :: MIT License
Classifier: Programming Language :: Python :: 3
Classifier: Programming Language :: Python :: 3.9
Classifier: Programming Language :: Python :: 3.10
Classifier: Programming Language :: Python :: 3.11
Requires-Dist: PyYAML (==6.0)
Requires-Dist: prometheus-client (==0.15.0)
Requires-Dist: pyedgeconnect (==0.15.3a1.dev0)
Requires-Dist: requests (==2.28.1)
Requires-Dist: tomli (==2.0.1)
